radar_mongodb/__init__.py
radar_mongodb/_query_manager.py
radar_mongodb/collections/__init__.py
radar_mongodb/collections/cboe.py
radar_mongodb/collections/open_interest.py
radar_mongodb/collections/spot.py
radar_mongodb-0.4.0.dist-info/WHEEL
radar_mongodb-0.4.0.dist-info/METADATA
radar_mongodb-0.4.0.dist-info/RECORD
